[
    {
        "id": "sxNt9g77PE0",
        "created_at": "2018-03-02T19:55:23-05:00",
        "updated_at": "2019-09-14T01:05:07-04:00",
        "width": 4288,
        "height": 2848,
        "color": "#0E0E08",
        "description": "Moving Day",
        "alt_description": "black and brown Dachshund standing in box",
        "urls": {
            "raw": "https://images.unsplash.com/photo-1520038410233-7141be7e6f97?ixlib=rb-1.2.1&ixid=eyJhcHBfaWQiOjg1NDc0fQ",
            "full": "https://images.unsplash.com/photo-1520038410233-7141be7e6f97?ixlib=rb-1.2.1&q=85&fm=jpg&crop=entropy&cs=srgb&ixid=eyJhcHBfaWQiOjg1NDc0fQ",
            "regular": "https://images.unsplash.com/photo-1520038410233-7141be7e6f97?ixlib=rb-1.2.1&q=80&fm=jpg&crop=entropy&cs=tinysrgb&w=1080&fit=max&ixid=eyJhcHBfaWQiOjg1NDc0fQ",
            "small": "https://images.unsplash.com/photo-1520038410233-7141be7e6f97?ixlib=rb-1.2.1&q=80&fm=jpg&crop=entropy&cs=tinysrgb&w=400&fit=max&ixid=eyJhcHBfaWQiOjg1NDc0fQ",
            "thumb": "https://images.unsplash.com/photo-1520038410233-7141be7e6f97?ixlib=rb-1.2.1&q=80&fm=jpg&crop=entropy&cs=tinysrgb&w=200&fit=max&ixid=eyJhcHBfaWQiOjg1NDc0fQ"
        },
        "links": {
            "self": "https://api.unsplash.com/photos/sxNt9g77PE0",
            "html": "https://unsplash.com/photos/sxNt9g77PE0",
            "download": "https://unsplash.com/photos/sxNt9g77PE0/download",
            "download_location": "https://api.unsplash.com/photos/sxNt9g77PE0/download"
        },
        "categories": [],
        "likes": 339,
        "liked_by_user": false,
        "current_user_collections": [],
        "user": {
            "id": "feqjmIJ1FI8",
            "updated_at": "2019-09-15T12:59:24-04:00",
            "username": "erdaest",
            "name": "Erda Estremera",
            "first_name": "Erda",
            "last_name": "Estremera",
            "twitter_username": null,
            "portfolio_url": "http://www.erdasart.com",
            "bio": "Life's meant to live in the moment. Photos won't go to the grave with me so why not share the beauty my eyes got to see while on this planet? Pay it forward. ",
            "location": "Raleigh, NC",
            "links": {
                "self": "https://api.unsplash.com/users/erdaest",
                "html": "https://unsplash.com/@erdaest",
                "photos": "https://api.unsplash.com/users/erdaest/photos",
                "likes": "https://api.unsplash.com/users/erdaest/likes",
                "portfolio": "https://api.unsplash.com/users/erdaest/portfolio",
                "following": "https://api.unsplash.com/users/erdaest/following",
                "followers": "https://api.unsplash.com/users/erdaest/followers"
            },
            "profile_image": {
                "small": "https://images.unsplash.com/profile-1539200104996-e47bf8f3fff9?ixlib=rb-1.2.1&q=80&fm=jpg&crop=faces&cs=tinysrgb&fit=crop&h=32&w=32",
                "medium": "https://images.unsplash.com/profile-1539200104996-e47bf8f3fff9?ixlib=rb-1.2.1&q=80&fm=jpg&crop=faces&cs=tinysrgb&fit=crop&h=64&w=64",
                "large": "https://images.unsplash.com/profile-1539200104996-e47bf8f3fff9?ixlib=rb-1.2.1&q=80&fm=jpg&crop=faces&cs=tinysrgb&fit=crop&h=128&w=128"
            },
            "instagram_username": "erdaestremera",
            "total_collections": 4,
            "total_likes": 831,
            "total_photos": 117,
            "accepted_tos": true
        },
        "exif": {
            "make": "NIKON CORPORATION",
            "model": "NIKON D300",
            "exposure_time": "1/60",
            "aperture": "4.2",
            "focal_length": "31.0",
            "iso": 1000
        },
        "location": {
            "title": null,
            "name": null,
            "city": null,
            "country": null,
            "position": {
                "latitude": null,
                "longitude": null
            }
        },
        "views": 2928674,
        "downloads": 36064
    },
    {
        "id": "9EAnS3X5Xf4",
        "created_at": "2017-06-07T21:54:23-04:00",
        "updated_at": "2019-09-14T01:05:42-04:00",
        "width": 3833,
        "height": 5749,
        "color": "#FAFAFA",
        "description": null,
        "alt_description": null,
        "urls": {
            "raw": "https://images.unsplash.com/photo-1496886833425-e0f25b335d03?ixlib=rb-1.2.1&ixid=eyJhcHBfaWQiOjg1NDc0fQ",
            "full": "https://images.unsplash.com/photo-1496886833425-e0f25b335d03?ixlib=rb-1.2.1&q=85&fm=jpg&crop=entropy&cs=srgb&ixid=eyJhcHBfaWQiOjg1NDc0fQ",
            "regular": "https://images.unsplash.com/photo-1496886833425-e0f25b335d03?ixlib=rb-1.2.1&q=80&fm=jpg&crop=entropy&cs=tinysrgb&w=1080&fit=max&ixid=eyJhcHBfaWQiOjg1NDc0fQ",
            "small": "https://images.unsplash.com/photo-1496886833425-e0f25b335d03?ixlib=rb-1.2.1&q=80&fm=jpg&crop=entropy&cs=tinysrgb&w=400&fit=max&ixid=eyJhcHBfaWQiOjg1NDc0fQ",
            "thumb": "https://images.unsplash.com/photo-1496886833425-e0f25b335d03?ixlib=rb-1.2.1&q=80&fm=jpg&crop=entropy&cs=tinysrgb&w=200&fit=max&ixid=eyJhcHBfaWQiOjg1NDc0fQ"
        },
        "links": {
            "self": "https://api.unsplash.com/photos/9EAnS3X5Xf4",
            "html": "https://unsplash.com/photos/9EAnS3X5Xf4",
            "download": "https://unsplash.com/photos/9EAnS3X5Xf4/download",
            "download_location": "https://api.unsplash.com/photos/9EAnS3X5Xf4/download"
        },
        "categories": [],
        "likes": 10,
        "liked_by_user": false,
        "current_user_collections": [],
        "user": {
            "id": "_zIhbG6jCHs",
            "updated_at": "2019-09-15T12:05:01-04:00",
            "username": "robsonhmorgan",
            "name": "Robson Hatsukami Morgan",
            "first_name": "Robson Hatsukami",
            "last_name": "Morgan",
            "twitter_username": "robsonhmorgan",
            "portfolio_url": "https://www.instagram.com/robsonhmorgan/",
            "bio": "Adventure and Travel Photographer based in Venice, CA. ",
            "location": "Venice Beach, CA",
            "links": {
                "self": "https://api.unsplash.com/users/robsonhmorgan",
                "html": "https://unsplash.com/@robsonhmorgan",
                "photos": "https://api.unsplash.com/users/robsonhmorgan/photos",
                "likes": "https://api.unsplash.com/users/robsonhmorgan/likes",
                "portfolio": "https://api.unsplash.com/users/robsonhmorgan/portfolio",
                "following": "https://api.unsplash.com/users/robsonhmorgan/following",
                "followers": "https://api.unsplash.com/users/robsonhmorgan/followers"
            },
            "profile_image": {
                "small": "https://images.unsplash.com/profile-fb-1470010123-640887b12fac.jpg?ixlib=rb-1.2.1&q=80&fm=jpg&crop=faces&cs=tinysrgb&fit=crop&h=32&w=32",
                "medium": "https://images.unsplash.com/profile-fb-1470010123-640887b12fac.jpg?ixlib=rb-1.2.1&q=80&fm=jpg&crop=faces&cs=tinysrgb&fit=crop&h=64&w=64",
                "large": "https://images.unsplash.com/profile-fb-1470010123-640887b12fac.jpg?ixlib=rb-1.2.1&q=80&fm=jpg&crop=faces&cs=tinysrgb&fit=crop&h=128&w=128"
            },
            "instagram_username": "robsonhmorgan",
            "total_collections": 0,
            "total_likes": 0,
            "total_photos": 92,
            "accepted_tos": true
        },
        "exif": {
            "make": null,
            "model": null,
            "exposure_time": null,
            "aperture": null,
            "focal_length": null,
            "iso": null
        },
        "location": {
            "title": "Venice, Los Angeles, United States",
            "name": "Venice, Los Angeles, United States",
            "city": "Los Angeles",
            "country": "United States",
            "position": {
                "latitude": 33.9850469,
                "longitude": -118.4694832
            }
        },
        "views": 35536,
        "downloads": 271
    },
    {
        "id": "Ltyfaze30SA",
        "created_at": "2019-08-07T19:17:14-04:00",
        "updated_at": "2019-09-14T01:05:06-04:00",
        "width": 3500,
        "height": 2333,
        "color": "#E0C6AC",
        "description": null,
        "alt_description": "orange fox",
        "urls": {
            "raw": "https://images.unsplash.com/photo-1565219043640-28bf17bc0bb5?ixlib=rb-1.2.1&ixid=eyJhcHBfaWQiOjg1NDc0fQ",
            "full": "https://images.unsplash.com/photo-1565219043640-28bf17bc0bb5?ixlib=rb-1.2.1&q=85&fm=jpg&crop=entropy&cs=srgb&ixid=eyJhcHBfaWQiOjg1NDc0fQ",
            "regular": "https://images.unsplash.com/photo-1565219043640-28bf17bc0bb5?ixlib=rb-1.2.1&q=80&fm=jpg&crop=entropy&cs=tinysrgb&w=1080&fit=max&ixid=eyJhcHBfaWQiOjg1NDc0fQ",
            "small": "https://images.unsplash.com/photo-1565219043640-28bf17bc0bb5?ixlib=rb-1.2.1&q=80&fm=jpg&crop=entropy&cs=tinysrgb&w=400&fit=max&ixid=eyJhcHBfaWQiOjg1NDc0fQ",
            "thumb": "https://images.unsplash.com/photo-1565219043640-28bf17bc0bb5?ixlib=rb-1.2.1&q=80&fm=jpg&crop=entropy&cs=tinysrgb&w=200&fit=max&ixid=eyJhcHBfaWQiOjg1NDc0fQ"
        },
        "links": {
            "self": "https://api.unsplash.com/photos/Ltyfaze30SA",
            "html": "https://unsplash.com/photos/Ltyfaze30SA",
            "download": "https://unsplash.com/photos/Ltyfaze30SA/download",
            "download_location": "https://api.unsplash.com/photos/Ltyfaze30SA/download"
        },
        "categories": [],
        "likes": 3,
        "liked_by_user": false,
        "current_user_collections": [],
        "user": {
            "id": "di1Xom3pChQ",
            "updated_at": "2019-09-16T02:47:25-04:00",
            "username": "olga_kononenko",
            "name": "Olga Kononenko",
            "first_name": "Olga",
            "last_name": "Kononenko",
            "twitter_username": null,
            "portfolio_url": "https://www.facebook.com/kononenko.olga",
            "bio": null,
            "location": "Kyiv, Ukraine",
            "links": {
                "self": "https://api.unsplash.com/users/olga_kononenko",
                "html": "https://unsplash.com/@olga_kononenko",
                "photos": "https://api.unsplash.com/users/olga_kononenko/photos",
                "likes": "https://api.unsplash.com/users/olga_kononenko/likes",
                "portfolio": "https://api.unsplash.com/users/olga_kononenko/portfolio",
                "following": "https://api.unsplash.com/users/olga_kononenko/following",
                "followers": "https://api.unsplash.com/users/olga_kononenko/followers"
            },
            "profile_image": {
                "small": "https://images.unsplash.com/profile-1567243086486-8b4896b2efd2image?ixlib=rb-1.2.1&q=80&fm=jpg&crop=faces&cs=tinysrgb&fit=crop&h=32&w=32",
                "medium": "https://images.unsplash.com/profile-1567243086486-8b4896b2efd2image?ixlib=rb-1.2.1&q=80&fm=jpg&crop=faces&cs=tinysrgb&fit=crop&h=64&w=64",
                "large": "https://images.unsplash.com/profile-1567243086486-8b4896b2efd2image?ixlib=rb-1.2.1&q=80&fm=jpg&crop=faces&cs=tinysrgb&fit=crop&h=128&w=128"
            },
            "instagram_username": "olga.kononenko.foto",
            "total_collections": 1,
            "total_likes": 1,
            "total_photos": 38,
            "accepted_tos": true
        },
        "exif": {
            "make": null,
            "model": null,
            "exposure_time": null,
            "aperture": null,
            "focal_length": null,
            "iso": null
        },
        "location": {
            "title": null,
            "name": null,
            "city": null,
            "country": null,
            "position": {
                "latitude": null,
                "longitude": null
            }
        },
        "views": 7676,
        "downloads": 40
    },
    {
        "id": "FTzRYeD5lAs",
        "created_at": "2018-11-25T11:58:30-05:00",
        "updated_at": "2019-09-14T01:05:19-04:00",
        "width": 5184,
        "height": 3456,
        "color": "#E5EFFC",
        "description": null,
        "alt_description": "short-coat brown dog lying on blue and white striped bedspread",
        "urls": {
            "raw": "https://images.unsplash.com/photo-1543164888-462c8603cbd9?ixlib=rb-1.2.1&ixid=eyJhcHBfaWQiOjg1NDc0fQ",
            "full": "https://images.unsplash.com/photo-1543164888-462c8603cbd9?ixlib=rb-1.2.1&q=85&fm=jpg&crop=entropy&cs=srgb&ixid=eyJhcHBfaWQiOjg1NDc0fQ",
            "regular": "https://images.unsplash.com/photo-1543164888-462c8603cbd9?ixlib=rb-1.2.1&q=80&fm=jpg&crop=entropy&cs=tinysrgb&w=1080&fit=max&ixid=eyJhcHBfaWQiOjg1NDc0fQ",
            "small": "https://images.unsplash.com/photo-1543164888-462c8603cbd9?ixlib=rb-1.2.1&q=80&fm=jpg&crop=entropy&cs=tinysrgb&w=400&fit=max&ixid=eyJhcHBfaWQiOjg1NDc0fQ",
            "thumb": "https://images.unsplash.com/photo-1543164888-462c8603cbd9?ixlib=rb-1.2.1&q=80&fm=jpg&crop=entropy&cs=tinysrgb&w=200&fit=max&ixid=eyJhcHBfaWQiOjg1NDc0fQ"
        },
        "links": {
            "self": "https://api.unsplash.com/photos/FTzRYeD5lAs",
            "html": "https://unsplash.com/photos/FTzRYeD5lAs",
            "download": "https://unsplash.com/photos/FTzRYeD5lAs/download",
            "download_location": "https://api.unsplash.com/photos/FTzRYeD5lAs/download"
        },
        "categories": [],
        "likes": 49,
        "liked_by_user": false,
        "current_user_collections": [],
        "user": {
            "id": "NTPdQ09dYUo",
            "updated_at": "2019-09-15T12:07:50-04:00",
            "username": "rstone_design",
            "name": "Ryan Stone",
            "first_name": "Ryan",
            "last_name": "Stone",
            "twitter_username": "ryanstonedesign",
            "portfolio_url": "https://www.instagram.com/ryanstonephotography/",
            "bio": "Landscape photographer in the Great Pacific Northwest. Follow me on Insta 👆",
            "location": "Seattle, WA",
            "links": {
                "self": "https://api.unsplash.com/users/rstone_design",
                "html": "https://unsplash.com/@rstone_design",
                "photos": "https://api.unsplash.com/users/rstone_design/photos",
                "likes": "https://api.unsplash.com/users/rstone_design/likes",
                "portfolio": "https://api.unsplash.com/users/rstone_design/portfolio",
                "following": "https://api.unsplash.com/users/rstone_design/following",
                "followers": "https://api.unsplash.com/users/rstone_design/followers"
            },
            "profile_image": {
                "small": "https://images.unsplash.com/profile-1561506196555-36159e538384?ixlib=rb-1.2.1&q=80&fm=jpg&crop=faces&cs=tinysrgb&fit=crop&h=32&w=32",
                "medium": "https://images.unsplash.com/profile-1561506196555-36159e538384?ixlib=rb-1.2.1&q=80&fm=jpg&crop=faces&cs=tinysrgb&fit=crop&h=64&w=64",
                "large": "https://images.unsplash.com/profile-1561506196555-36159e538384?ixlib=rb-1.2.1&q=80&fm=jpg&crop=faces&cs=tinysrgb&fit=crop&h=128&w=128"
            },
            "instagram_username": "ryanstonedesign",
            "total_collections": 15,
            "total_likes": 310,
            "total_photos": 196,
            "accepted_tos": true
        },
        "exif": {
            "make": "Canon",
            "model": "Canon EOS REBEL T5",
            "exposure_time": "1/25",
            "aperture": "8.0",
            "focal_length": "28.0",
            "iso": 3200
        },
        "location": {
            "title": null,
            "name": null,
            "city": null,
            "country": null,
            "position": {
                "latitude": null,
                "longitude": null
            }
        },
        "views": 477397,
        "downloads": 2303
    },
    {
        "id": "BHO7K8Zf16w",
        "created_at": "2018-03-17T14:01:24-04:00",
        "updated_at": "2019-09-14T01:05:39-04:00",
        "width": 4000,
        "height": 6000,
        "color": "#100F12",
        "description": null,
        "alt_description": "short-coated white and brown puppy",
        "urls": {
            "raw": "https://images.unsplash.com/photo-1521309569781-7bcd429eb2f6?ixlib=rb-1.2.1&ixid=eyJhcHBfaWQiOjg1NDc0fQ",
            "full": "https://images.unsplash.com/photo-1521309569781-7bcd429eb2f6?ixlib=rb-1.2.1&q=85&fm=jpg&crop=entropy&cs=srgb&ixid=eyJhcHBfaWQiOjg1NDc0fQ",
            "regular": "https://images.unsplash.com/photo-1521309569781-7bcd429eb2f6?ixlib=rb-1.2.1&q=80&fm=jpg&crop=entropy&cs=tinysrgb&w=1080&fit=max&ixid=eyJhcHBfaWQiOjg1NDc0fQ",
            "small": "https://images.unsplash.com/photo-1521309569781-7bcd429eb2f6?ixlib=rb-1.2.1&q=80&fm=jpg&crop=entropy&cs=tinysrgb&w=400&fit=max&ixid=eyJhcHBfaWQiOjg1NDc0fQ",
            "thumb": "https://images.unsplash.com/photo-1521309569781-7bcd429eb2f6?ixlib=rb-1.2.1&q=80&fm=jpg&crop=entropy&cs=tinysrgb&w=200&fit=max&ixid=eyJhcHBfaWQiOjg1NDc0fQ"
        },
        "links": {
            "self": "https://api.unsplash.com/photos/BHO7K8Zf16w",
            "html": "https://unsplash.com/photos/BHO7K8Zf16w",
            "download": "https://unsplash.com/photos/BHO7K8Zf16w/download",
            "download_location": "https://api.unsplash.com/photos/BHO7K8Zf16w/download"
        },
        "categories": [],
        "likes": 123,
        "liked_by_user": false,
        "current_user_collections": [],
        "user": {
            "id": "K5MAoqrVQBY",
            "updated_at": "2019-09-15T12:58:16-04:00",
            "username": "isaacdavis",
            "name": "Isaac Davis",
            "first_name": "Isaac",
            "last_name": "Davis",
            "twitter_username": null,
            "portfolio_url": null,
            "bio": null,
            "location": null,
            "links": {
                "self": "https://api.unsplash.com/users/isaacdavis",
                "html": "https://unsplash.com/@isaacdavis",
                "photos": "https://api.unsplash.com/users/isaacdavis/photos",
                "likes": "https://api.unsplash.com/users/isaacdavis/likes",
                "portfolio": "https://api.unsplash.com/users/isaacdavis/portfolio",
                "following": "https://api.unsplash.com/users/isaacdavis/following",
                "followers": "https://api.unsplash.com/users/isaacdavis/followers"
            },
            "profile_image": {
                "small": "https://images.unsplash.com/profile-fb-1506184266-b33af39dbc82.jpg?ixlib=rb-1.2.1&q=80&fm=jpg&crop=faces&cs=tinysrgb&fit=crop&h=32&w=32",
                "medium": "https://images.unsplash.com/profile-fb-1506184266-b33af39dbc82.jpg?ixlib=rb-1.2.1&q=80&fm=jpg&crop=faces&cs=tinysrgb&fit=crop&h=64&w=64",
                "large": "https://images.unsplash.com/profile-fb-1506184266-b33af39dbc82.jpg?ixlib=rb-1.2.1&q=80&fm=jpg&crop=faces&cs=tinysrgb&fit=crop&h=128&w=128"
            },
            "instagram_username": "iSak_Davis",
            "total_collections": 0,
            "total_likes": 8,
            "total_photos": 3,
            "accepted_tos": false
        },
        "exif": {
            "make": "SONY",
            "model": "ILCE-7",
            "exposure_time": "1/80",
            "aperture": null,
            "focal_length": null,
            "iso": 400
        },
        "location": {
            "title": null,
            "name": null,
            "city": null,
            "country": null,
            "position": {
                "latitude": null,
                "longitude": null
            }
        },
        "views": 924660,
        "downloads": 6473
    }
]